Metadata-Version: 2.1
Name: liqpay3
Version: 0.1
Summary: Liqpay client python 3+
Home-page: UNKNOWN
Author-email: mmi200212@gmail.com
License: UNKNOWN
Platform: UNKNOWN
